gptbot/__init__.py
gptbot/__main__.py
gptbot/assets/logo.png
gptbot/callbacks/__init__.py
gptbot/callbacks/invite.py
gptbot/callbacks/join.py
gptbot/callbacks/message.py
gptbot/callbacks/roommember.py
gptbot/callbacks/sync.py
gptbot/classes/__init__.py
gptbot/classes/bot.py
gptbot/classes/dict.py
gptbot/classes/exceptions.py
gptbot/classes/logging.py
gptbot/classes/trackingmore.py
gptbot/classes/wolframalpha.py
gptbot/classes/ai/__init__.py
gptbot/classes/ai/base.py
gptbot/classes/ai/google.py
gptbot/classes/ai/openai.py
gptbot/commands/__init__.py
gptbot/commands/botinfo.py
gptbot/commands/calculate.py
gptbot/commands/chat.py
gptbot/commands/classify.py
gptbot/commands/coin.py
gptbot/commands/custom.py
gptbot/commands/dice.py
gptbot/commands/help.py
gptbot/commands/ignoreolder.py
gptbot/commands/imagine.py
gptbot/commands/newroom.py
gptbot/commands/parcel.py
gptbot/commands/privacy.py
gptbot/commands/roomsettings.py
gptbot/commands/space.py
gptbot/commands/stats.py
gptbot/commands/systemmessage.py
gptbot/commands/tts.py
gptbot/commands/unknown.py
gptbot/migrations/__init__.py
gptbot/migrations/migration_1.py
gptbot/migrations/migration_2.py
gptbot/migrations/migration_3.py
gptbot/migrations/migration_4.py
gptbot/migrations/migration_5.py
gptbot/migrations/migration_6.py
gptbot/migrations/migration_7.py
gptbot/migrations/migration_8.py
gptbot/tools/__init__.py
gptbot/tools/base.py
gptbot/tools/datetime.py
gptbot/tools/dice.py
gptbot/tools/geocode.py
gptbot/tools/imagedescription.py
gptbot/tools/imagine.py
gptbot/tools/newroom.py
gptbot/tools/weather.py
gptbot/tools/webrequest.py
gptbot/tools/websearch.py
gptbot/tools/wikipedia.py
matrix_gptbot-0.3.21.dist-info/METADATA
matrix_gptbot-0.3.21.dist-info/WHEEL
matrix_gptbot-0.3.21.dist-info/entry_points.txt
matrix_gptbot-0.3.21.dist-info/licenses/LICENSE
matrix_gptbot-0.3.21.dist-info/RECORD
