Metadata-Version: 2.3
Name: matrix-gptbot
Version: 0.3.21
Summary: Multifunctional Chatbot for Matrix
Project-URL: Homepage, https://git.private.coffee/privatecoffee/matrix-gptbot
Project-URL: Bug Tracker, https://git.private.coffee/privatecoffee/matrix-gptbot/issues
Project-URL: Source Code, https://git.private.coffee/privatecoffee/matrix-gptbot
Author-email: Kumi <gptbot@kumi.email>, "Private.coffee Team" <support@private.coffee>
License: Copyright (c) 2023-2024 Kumi Mitterer <gptbot@kumi.email>, Private.coffee Team
License-File: LICENSE
Classifier: License :: OSI Approved :: MIT License
Classifier: Operating System :: OS Independent
Classifier: Programming Language :: Python :: 3
Requires-Python: >=3.10
Requires-Dist: future>=1.0.0
Requires-Dist: markdown2[all]
Requires-Dist: matrix-nio[e2e]>=0.24.0
Requires-Dist: pillow
Requires-Dist: python-magic
Requires-Dist: tiktoken
Provides-Extra: all
Requires-Dist: beautifulsoup4; extra == 'all'
Requires-Dist: geopy; extra == 'all'
Requires-Dist: google-generativeai; extra == 'all'
Requires-Dist: openai>=1.2; extra == 'all'
Requires-Dist: pydub; extra == 'all'
Requires-Dist: trackingmore-api-tool; extra == 'all'
Requires-Dist: wolframalpha; extra == 'all'
Provides-Extra: dev
Requires-Dist: beautifulsoup4; extra == 'dev'
Requires-Dist: black; extra == 'dev'
Requires-Dist: build; extra == 'dev'
Requires-Dist: geopy; extra == 'dev'
Requires-Dist: google-generativeai; extra == 'dev'
Requires-Dist: hatchling; extra == 'dev'
Requires-Dist: openai>=1.2; extra == 'dev'
Requires-Dist: pydub; extra == 'dev'
Requires-Dist: ruff; extra == 'dev'
Requires-Dist: trackingmore-api-tool; extra == 'dev'
Requires-Dist: twine; extra == 'dev'
Requires-Dist: wolframalpha; extra == 'dev'
Provides-Extra: google
Requires-Dist: google-generativeai; extra == 'google'
Provides-Extra: openai
Requires-Dist: openai>=1.2; extra == 'openai'
Requires-Dist: pydub; extra == 'openai'
Provides-Extra: trackingmore
Requires-Dist: trackingmore-api-tool; extra == 'trackingmore'
Provides-Extra: wolframalpha
Requires-Dist: wolframalpha; extra == 'wolframalpha'
